[
    {
      "title": "Willkommen im Hauptquartier (HQ)!",
      "text": "Dies ist Ihre Standard-Startseite.",
      "buttons": [
        { "text": "Weiter", "action": "next" }
      ]
    },
    {
      "title": "Die Seitenleiste",
      "text": "Die Seitenleiste zeigt Ihnen einige Schnellzugriffslinks für Ihre Apps.",
      "attachTo": { "element": ".app-sidebar", "on": "right" },      
      "onShow": "expandSidebar",
      "buttons": [
        {"text":"Zurück", "action": "back" },
        {"text":"Weiter", "action": "next" }
      ]
    },
    {
      "title": "Hell-/Dunkelmodus umschalten",
      "text": "Mit diesen Schaltflächen können Sie zwischen Hell- und Dunkelmodus wechseln. Probieren Sie es aus, indem Sie auf die Schaltflächen klicken.",
      "attachTo": { "element": "#bd-theme", "on": "right" },     
      "buttons": [
        {"text":"Zurück", "action": "back" },
        {"text":"Weiter", "action": "next" }
      ]
    },
    {
      "title": "Angeheftete Apps",
      "text": "Ihre angehefteten Apps werden in diesem Menü angezeigt.",
      "attachTo": { "element": "#pinned-apps", "on": "right" },     
      "buttons": [
        {"text":"Zurück", "action": "back" },
        {"text":"Weiter", "action": "next" }
      ]
    },
    {
      "title": "Ausgewählte Apps",
      "text": "Ihre ausgewählten Apps werden hier angezeigt.",
      "attachTo": { "element": "#featured-apps", "on": "right" },     
      "buttons": [
        {"text":"Zurück", "action": "back" },
        {"text":"Weiter", "action": "next" }
      ]
    },
    {
      "title": "Apps verwalten",
      "text": "Über diesen Link können Sie weitere Apps installieren, sie anheften und in der Seitenleiste anzeigen lassen.",
      "attachTo": { "element": "#manage-apps", "on": "right" },     
      "buttons": [
        {"text":"Zurück", "action": "back" },
        {"text":"Weiter", "action": "next" }
      ]
    },
    {
      "title": "Die Kopfzeile",
      "text": "Die Kopfzeile enthält Schaltflächen zum Ein- und Ausblenden der Seitenleiste, Ihren aktuellen Ort und andere Schnelllinks.",
      "attachTo": { "element": ".app-header", "on": "bottom" },     
      "onShow": "collapseSidebar",
      "buttons": [
        {"text":"Zurück", "action": "back" },
        {"text":"Weiter", "action": "next" }
      ]

    },
    {
      "title": "Seitenleiste umschalten",
      "text": "Die Seitenleiste kann zwischen der erweiterten und der verkleinerten Version umgeschaltet werden. Auf kleineren Bildschirmen ist die Seitenleiste ausgeblendet und kann über diese Schaltfläche aufgerufen werden.",
      "attachTo": { "element": "#toggle-sidebar", "on": "bottom" },     
      "buttons": [
        {"text":"Zurück", "action": "back" },
        {"text":"Weiter", "action": "next" }
      ]
    },
    {
      "title": "Suchschaltfläche",
      "text": "Sie können Kontakte, Hashtags, Foren und Hilfedateien schnell durchsuchen.",
      "attachTo": { "element": "#nav-search-btn", "on": "bottom" },     
      "buttons": [
        {"text":"Zurück", "action": "back" },
        {"text":"Weiter", "action": "next" }
      ]
    },
    {
      "title": "Benachrichtigungen",
      "text": "Über dieses Dropdown-Menü können Sie auf Ihre Benachrichtigungen zugreifen.",
      "attachTo": { "element": "#notifications-btn-1", "on": "bottom" },     
      "buttons": [
        {"text":"Zurück", "action": "back" },
        {"text":"Weiter", "action": "next" }
      ]
    },
    {
      "title": "Benutzermenü",
      "text": "Hier können Sie ihr(e) Profil(e) anzeigen/bearbeiten, zu anderen Kanälen wechseln, Einstellungen anzeigen oder sich abmelden.",
      "attachTo": { "element": ".user-menu", "on": "bottom" },     
      "buttons": [
        {"text":"Zurück", "action": "back" },
        {"text":"Weiter", "action": "next" }
      ]
    },
    {
      "title": "Aktivitätenübersicht",
      "text": "Ihre kürzlich hochgeladenen Fotos, Beiträge, Webseiten, Wiki-Seiten usw. werden hier angezeigt.",
      "attachTo": { "element": "#channel-activities", "on": "right" },     
      "buttons": [
        {"text":"Zurück", "action": "back" },
        {"text":"Weiter", "action": "next" }
      ]
    },
    {
      "title": "Nachrichten-Widget",
      "text": "Dieses Widget zeigt Ihnen die neuesten Beiträge aus Ihrem Netzwerk, Direktnachrichten, mit Stern markierte Beiträge (falls aktiviert), gespeicherte Ordner (falls aktiviert) und Benachrichtigungen an.",
      "attachTo": { "element": "#messages-widget", "on": "left" },     
      "onShow": "toggleOffcanvas",
      "buttons": [
        {"text":"Zurück", "action": "back" },
        {"text":"Tour beenden", "action": "cancel" }
      ]
    }
 ]
